data_processing/__init__.py
data_processing/data_processing.py
environ/__init__.py
environ/air_traffic.py
environ/blackhole.py
environ/chemical_reaction.py
environ/lorenz.py
environ/model.py
environ/robot_move.py
environ/sensor_net.py
environ/sin_cos.py
environ/slide_slip_veh.py
environ/ugv.py
environ/ugv2.py
environ/wiener_velocity.py
filter/EKF.py
filter/HuberEKF.py
filter/NANO.py
filter/PF.py
filter/PLF.py
filter/UKF.py
filter/__init__.py
filter/iEKF.py
filter/main.py
filter/utils.py
NANO_filter-1.0.0.dist-info/LICENSE
NANO_filter-1.0.0.dist-info/METADATA
NANO_filter-1.0.0.dist-info/WHEEL
NANO_filter-1.0.0.dist-info/top_level.txt
NANO_filter-1.0.0.dist-info/RECORD
