Metadata-Version: 2.1
Name: NANO-filter
Version: 1.0.0
Summary: Nonlinear Bayesian Filtering with Natural Gradient Gaussian Approximation
Home-page: https://github.com/TianyiMehdi/NANO-filter
Author: Tianyi Zhang
Author-email: zhangtia24@mails.tsinghua.edu.cn
License: MIT
Classifier: Programming Language :: Python :: 3
Classifier: License :: OSI Approved :: MIT License
Classifier: Operating System :: OS Independent
Requires-Python: >=3.8
License-File: LICENSE
Requires-Dist: autograd ==1.6.2
Requires-Dist: dataclasses-json ==0.6.7
Requires-Dist: einops ==0.8.0
Requires-Dist: filterpy ==1.4.5
Requires-Dist: matplotlib ==3.8.2
Requires-Dist: numpy ==2.1.2
Requires-Dist: pandas ==2.2.3
Requires-Dist: scipy ==1.14.1
Requires-Dist: seaborn ==0.13.2
Requires-Dist: tqdm ==4.66.1
